skyworker_processor/__init__.py
skyworker_processor/core/__init__.py
skyworker_processor/core/config.py
skyworker_processor/core/processor.py
skyworker_dev_petroleum_price_random-0.1.0.dist-info/LICENSE
skyworker_dev_petroleum_price_random-0.1.0.dist-info/METADATA
skyworker_dev_petroleum_price_random-0.1.0.dist-info/WHEEL
skyworker_dev_petroleum_price_random-0.1.0.dist-info/top_level.txt
skyworker_dev_petroleum_price_random-0.1.0.dist-info/RECORD
