Metadata-Version: 2.1
Name: skyworker-dev-petroleum-price-random
Version: 0.1.0
Summary: Skyworker AI Processor
Home-page: http://example.com
Author: Temuri Takalandze
Author-email: welcome@omedia.dev
License: UNKNOWN
Platform: UNKNOWN
Classifier: Programming Language :: Python
Classifier: Programming Language :: Python :: 3.6
Classifier: Programming Language :: Python :: 3.7
Classifier: Programming Language :: Python :: 3.8
Classifier: Programming Language :: Python :: 3.9
Classifier: License :: Other/Proprietary License
Classifier: Operating System :: OS Independent
Requires-Python: >=3.6
License-File: LICENSE
Requires-Dist: pandas (==1.3.0)
